arcade_pagerduty/__init__.py
arcade_pagerduty/__main__.py
arcade_pagerduty/client.py
arcade_pagerduty/constants.py
arcade_pagerduty/models/__init__.py
arcade_pagerduty/models/enums.py
arcade_pagerduty/models/mappers.py
arcade_pagerduty/models/api_responses/__init__.py
arcade_pagerduty/models/api_responses/escalation_policies.py
arcade_pagerduty/models/api_responses/incidents.py
arcade_pagerduty/models/api_responses/log_entries.py
arcade_pagerduty/models/api_responses/oncalls.py
arcade_pagerduty/models/api_responses/schedules.py
arcade_pagerduty/models/api_responses/services.py
arcade_pagerduty/models/api_responses/teams.py
arcade_pagerduty/models/api_responses/users.py
arcade_pagerduty/models/tool_outputs/__init__.py
arcade_pagerduty/models/tool_outputs/common.py
arcade_pagerduty/models/tool_outputs/escalation_policies.py
arcade_pagerduty/models/tool_outputs/incidents.py
arcade_pagerduty/models/tool_outputs/log_entries.py
arcade_pagerduty/models/tool_outputs/oncalls.py
arcade_pagerduty/models/tool_outputs/schedules.py
arcade_pagerduty/models/tool_outputs/services.py
arcade_pagerduty/models/tool_outputs/teams.py
arcade_pagerduty/models/tool_outputs/user_context.py
arcade_pagerduty/models/tool_outputs/users.py
arcade_pagerduty/tools/__init__.py
arcade_pagerduty/tools/escalation_policies.py
arcade_pagerduty/tools/incidents.py
arcade_pagerduty/tools/log_entries.py
arcade_pagerduty/tools/oncalls.py
arcade_pagerduty/tools/schedules.py
arcade_pagerduty/tools/services.py
arcade_pagerduty/tools/teams.py
arcade_pagerduty/tools/user_context.py
arcade_pagerduty/tools/users.py
arcade_pagerduty/utils/__init__.py
arcade_pagerduty/utils/auth_utils.py
arcade_pagerduty/utils/fuzzy.py
arcade_pagerduty/utils/response_utils.py
arcade_pagerduty-0.2.0.dist-info/METADATA
arcade_pagerduty-0.2.0.dist-info/WHEEL
arcade_pagerduty-0.2.0.dist-info/entry_points.txt
arcade_pagerduty-0.2.0.dist-info/licenses/LICENSE
arcade_pagerduty-0.2.0.dist-info/RECORD
